__init__.py
jsoncustom.py
jsoncustom-0.0.2.dist-info/LICENSE
jsoncustom-0.0.2.dist-info/METADATA
jsoncustom-0.0.2.dist-info/WHEEL
jsoncustom-0.0.2.dist-info/top_level.txt
jsoncustom-0.0.2.dist-info/RECORD
