Metadata-Version: 2.1
Name: jsoncustom
Version: 0.0.2
Summary: Легкая работа с json
Author-email: plp-kolyan <plp-kolyan@mail.ru>
License: Copyright (c) 2018 The Python Packaging Authority        
Project-URL: Homepage, https://github.com/plp-kolyan/jsoncustom
Classifier: Programming Language :: Python :: 3
Classifier: License :: OSI Approved :: MIT License
Classifier: Operating System :: OS Independent
Requires-Python: >=3.7
License-File: LICENSE
